mano_datahub_mcp-0.0.5.dist-info/licenses/LICENSE
mcp_server_datahub/__init__.py
mcp_server_datahub/__main__.py
mcp_server_datahub/_telemetry.py
mcp_server_datahub/_version.py
mcp_server_datahub/mcp_server.py
mcp_server_datahub/py.typed
mcp_server_datahub/gql/entity_details.gql
mcp_server_datahub/gql/queries.gql
mcp_server_datahub/gql/query_by_keywords.gql
mcp_server_datahub/gql/search.gql
mano_datahub_mcp-0.0.5.dist-info/METADATA
mano_datahub_mcp-0.0.5.dist-info/WHEEL
mano_datahub_mcp-0.0.5.dist-info/entry_points.txt
mano_datahub_mcp-0.0.5.dist-info/top_level.txt
mano_datahub_mcp-0.0.5.dist-info/RECORD
