Metadata-Version: 2.4
Name: mano-datahub-mcp
Version: 0.0.5
Summary: A Model Context Protocol (MCP) server for DataHub
License-Expression: Apache-2.0
Project-URL: Source, https://github.com/mano1233/mcp-server-datahub
Project-URL: Documentation, https://docs.datahub.com/docs/features/feature-guides/mcp
Requires-Python: >=3.10
License-File: LICENSE
Requires-Dist: acryl-datahub==1.2.0.2
Requires-Dist: asyncer>=0.0.8
Requires-Dist: fastmcp==2.10.5
Requires-Dist: jmespath~=1.0.1
Dynamic: license-file
